dtw_flex/__init__.py
dtw_flex/core/__init__.py
dtw_flex/core/dtw.py
dtw_flex/core/utils.py
dtw_flex/core/visual_select.py
dtw_flex/core_cython/dtw_cy.c
dtw_flex/core_cython/dtw_cy.cp311-win_amd64.pyd
dtw_flex/core_cython/dtw_cy.pyx
dtw_flex/core_cython/test.py
dtw_flex-0.1.0.dist-info/licenses/LICENSE
dtw_flex-0.1.0.dist-info/METADATA
dtw_flex-0.1.0.dist-info/WHEEL
dtw_flex-0.1.0.dist-info/top_level.txt
dtw_flex-0.1.0.dist-info/RECORD
