Metadata-Version: 2.4
Name: dtw_flex
Version: 0.1.0
Summary: dynamic time warping with amplitude and offset correction
Author-email: Alexander Meire <alexander.meire@gmail.com>
License: GPLv3
Project-URL: Homepage, https://github.com/aifm00/dtw_flex
Keywords: dtw
Classifier: Programming Language :: Python :: 3
Requires-Python: >=3.11
License-File: LICENSE
Requires-Dist: numpy>=2.0.0
Requires-Dist: pandas>=2.0.2
Requires-Dist: matplotlib>=3.7.1
Requires-Dist: ipympl>=0.9.3
Dynamic: license-file
